exchangeratesapi/__init__.py
exchangeratesapi/__main__.py
exchangeratesapi/currency.py
exchangeratesapi/functions.py
exchangeratesapi/main.py
exchangeratesapi/rates.py
exchangeratesapi-0.1.0.dist-info/LICENSE
exchangeratesapi-0.1.0.dist-info/METADATA
exchangeratesapi-0.1.0.dist-info/WHEEL
exchangeratesapi-0.1.0.dist-info/entry_points.txt
exchangeratesapi-0.1.0.dist-info/top_level.txt
exchangeratesapi-0.1.0.dist-info/RECORD
