Metadata-Version: 2.1
Name: exchangeratesapi
Version: 0.1.0
Summary: Python wrapper on Exchange Rates API
Home-page: https://github.com/jsporna/pyexchangeratesapi
Author: Jakub Spórna <jakub.sporna@gmail.com>
Author-email: jakub@sporna.dev
License: UNKNOWN
Keywords: Exchange,Rates,Rest API
Platform: UNKNOWN
Classifier: License :: OSI Approved :: Apache Software License
Classifier: Programming Language :: Python :: 3
Classifier: Programming Language :: Python :: 3.8
Classifier: Programming Language :: Python :: Implementation :: CPython
